timezone_embed/__main__.py
timezone_embed-0.1.1.dist-info/METADATA
timezone_embed-0.1.1.dist-info/WHEEL
timezone_embed-0.1.1.dist-info/entry_points.txt
timezone_embed-0.1.1.dist-info/RECORD
